dinnovation/__init__.py
dinnovation/version.py
dinnovation/collection/__init__.py
dinnovation-0.3.0.dist-info/LICENSE
dinnovation-0.3.0.dist-info/METADATA
dinnovation-0.3.0.dist-info/WHEEL
dinnovation-0.3.0.dist-info/top_level.txt
dinnovation-0.3.0.dist-info/RECORD
